Metadata-Version: 2.4
Name: netbox-slm
Version: 1.8.3
Summary: Software Lifecycle Management Netbox Plugin
Author-email: ICTU <open-source-projects@ictu.nl>
License: Apache-2.0
Project-URL: Homepage, https://github.com/ICTU/netbox_slm/
Project-URL: Changelog, https://github.com/ICTU/netbox_slm/blob/master/CHANGELOG.md
Project-URL: Issues, https://github.com/ICTU/netbox_slm/issues/
Classifier: Development Status :: 5 - Production/Stable
Classifier: Environment :: Plugins
Classifier: Environment :: Web Environment
Classifier: Framework :: Django
Classifier: Intended Audience :: Developers
Classifier: Intended Audience :: System Administrators
Classifier: License :: OSI Approved :: Apache Software License
Classifier: Operating System :: OS Independent
Classifier: Programming Language :: Python :: 3
Classifier: Programming Language :: Python :: 3 :: Only
Classifier: Programming Language :: Python :: 3.11
Classifier: Programming Language :: Python :: 3.12
Classifier: Programming Language :: Python :: 3.13
Classifier: Programming Language :: Python
Classifier: Topic :: Internet :: WWW/HTTP
Classifier: Topic :: Internet :: WWW/HTTP :: Dynamic Content
Requires-Python: >=3.11
License-File: LICENSE
Requires-Dist: license-expression==30.4.1
Provides-Extra: build
Requires-Dist: build==1.2.2.post1; extra == "build"
Requires-Dist: setuptools==75.8.0; extra == "build"
Requires-Dist: twine==6.1.0; extra == "build"
Provides-Extra: ci
Requires-Dist: coverage==7.6.11; extra == "ci"
Requires-Dist: ruff==0.9.6; extra == "ci"
Dynamic: license-file
